{"agent_silence_seconds":1032.5,"agent_silent":false,"circuit_breakers":{"alpaca":{"failure_count":0,"last_failure_time":null,"name":"alpaca","state":"CLOSED"},"binance_fapi":{"failure_count":0,"last_failure_time":null,"name":"binance_fapi","state":"CLOSED"},"binance_spot":{"failure_count":0,"last_failure_time":null,"name":"binance_spot","state":"CLOSED"}},"cycle_count":253,"error_count":452,"heartbeat_age_seconds":180.1,"last_trigger":"XAU-USD consensus BUY (61%)","last_trigger_time":"2026-03-14T16:43:27.051890+00:00","module_failures":null,"recent_errors":[{"error":"Extra data: line 34 column 1 (char 566)","ts":"2026-03-03T11:11:49.544487+00:00"},{"error":"Extra data: line 34 column 1 (char 566)","ts":"2026-03-03T11:13:15.609115+00:00"},{"error":"Extra data: line 34 column 1 (char 566)","ts":"2026-03-03T11:15:32.774433+00:00"},{"error":"Extra data: line 34 column 1 (char 566)","ts":"2026-03-03T11:17:40.601724+00:00"},{"error":"Extra data: line 34 column 1 (char 566)","ts":"2026-03-03T11:23:56.688921+00:00"}],"signals_failed":0,"signals_ok":19,"status":"healthy"}