{"agent_silence_seconds":90731.0,"agent_silent":true,"cycle_count":317,"error_count":319,"heartbeat_age_seconds":390.5,"last_trigger":"ETH-USD consensus SELL (38%)","last_trigger_time":"2026-03-01T20:35:05.032800+00:00","module_failures":null,"recent_errors":[{"error":"Extra data: line 34 column 1 (char 566)","ts":"2026-03-02T21:01:28.610615+00:00"},{"error":"Extra data: line 34 column 1 (char 566)","ts":"2026-03-02T21:09:22.133339+00:00"},{"error":"Extra data: line 34 column 1 (char 566)","ts":"2026-03-02T21:21:06.619556+00:00"},{"error":"Extra data: line 34 column 1 (char 566)","ts":"2026-03-02T21:29:04.595656+00:00"},{"error":"Extra data: line 34 column 1 (char 566)","ts":"2026-03-02T21:40:45.553085+00:00"}],"signals_failed":0,"signals_ok":0,"status":"stale"}