{"monte_carlo":{"AMD":{"atr_pct":0.63,"drift_annual":-0.4628,"expected_return_1d":{"mean_pct":-0.18,"skew":0.01,"std_pct":0.31},"expected_return_3d":{"mean_pct":-0.55,"skew":0.02,"std_pct":0.54},"p_stop_hit_1d":0.0,"p_stop_hit_3d":0.095,"p_up":0.279,"price_bands_1d":{"25":199.37,"5":198.74,"50":199.78,"75":200.2,"95":200.83},"price_bands_3d":{"25":198.33,"5":197.26,"50":199.05,"75":199.77,"95":200.85},"price_usd":200.15,"stop_price":197.63,"volatility_annual":0.05},"AMZN":{"atr_pct":0.48,"drift_annual":-0.6668,"expected_return_1d":{"mean_pct":-0.26,"skew":0.01,"std_pct":0.31},"expected_return_3d":{"mean_pct":-0.79,"skew":0.02,"std_pct":0.54},"p_stop_hit_1d":0.012,"p_stop_hit_3d":0.381,"p_up":0.2,"price_bands_1d":{"25":213.86,"5":213.21,"50":214.31,"75":214.76,"95":215.42},"price_bands_3d":{"25":212.4,"5":211.28,"50":213.18,"75":213.96,"95":215.09},"price_usd":214.88,"stop_price":212.82,"volatility_annual":0.05},"BTC-USD":{"atr_pct":0.72,"drift_annual":-0.6668,"expected_return_1d":{"mean_pct":-0.26,"skew":0.01,"std_pct":0.32},"expected_return_3d":{"mean_pct":-0.79,"skew":0.02,"std_pct":0.54},"p_stop_hit_1d":0.0,"p_stop_hit_3d":0.117,"p_up":0.2,"price_bands_1d":{"25":72847.86,"5":72627.56,"50":73005.37,"75":73163.21,"95":73385.13},"price_bands_3d":{"25":72348.18,"5":71969.66,"50":72619.34,"75":72891.51,"95":73274.88},"price_usd":73199.15,"stop_price":72145.08,"volatility_annual":0.05},"ETH-USD":{"atr_pct":0.86,"drift_annual":-0.6668,"expected_return_1d":{"mean_pct":-0.26,"skew":0.01,"std_pct":0.32},"expected_return_3d":{"mean_pct":-0.79,"skew":0.02,"std_pct":0.55},"p_stop_hit_1d":0.0,"p_stop_hit_3d":0.045,"p_up":0.2,"price_bands_1d":{"25":2130.52,"5":2123.88,"50":2135.06,"75":2139.61,"95":2146.3},"price_bands_3d":{"25":2115.96,"5":2104.54,"50":2123.77,"75":2131.61,"95":2143.18},"price_usd":2140.73,"stop_price":2103.91,"volatility_annual":0.05},"META":{"atr_pct":0.43,"drift_annual":-0.4594,"expected_return_1d":{"mean_pct":-0.18,"skew":0.01,"std_pct":0.31},"expected_return_3d":{"mean_pct":-0.55,"skew":0.02,"std_pct":0.54},"p_stop_hit_1d":0.013,"p_stop_hit_3d":0.283,"p_up":0.281,"price_bands_1d":{"25":663.27,"5":661.32,"50":664.7,"75":666.14,"95":668.1},"price_bands_3d":{"25":659.8,"5":656.45,"50":662.28,"75":664.76,"95":668.15},"price_usd":665.92,"stop_price":660.19,"volatility_annual":0.05},"MU":{"atr_pct":0.84,"drift_annual":-0.6309,"expected_return_1d":{"mean_pct":-0.25,"skew":0.01,"std_pct":0.31},"expected_return_3d":{"mean_pct":-0.75,"skew":0.02,"std_pct":0.54},"p_stop_hit_1d":0.0,"p_stop_hit_3d":0.039,"p_up":0.213,"price_bands_1d":{"25":404.87,"5":403.69,"50":405.75,"75":406.63,"95":407.82},"price_bands_3d":{"25":402.2,"5":400.18,"50":403.72,"75":405.24,"95":407.3},"price_usd":406.77,"stop_price":399.94,"volatility_annual":0.05},"SMCI":{"atr_pct":1.07,"drift_annual":-0.4779,"expected_return_1d":{"mean_pct":-0.19,"skew":0.01,"std_pct":0.32},"expected_return_3d":{"mean_pct":-0.57,"skew":0.02,"std_pct":0.55},"p_stop_hit_1d":0.0,"p_stop_hit_3d":0.002,"p_up":0.273,"price_bands_1d":{"25":32.35,"5":32.25,"50":32.42,"75":32.49,"95":32.59},"price_bands_3d":{"25":32.18,"5":32.01,"50":32.3,"75":32.42,"95":32.59},"price_usd":32.485,"stop_price":31.79,"volatility_annual":0.05},"XAG-USD":{"atr_pct":0.89,"drift_annual":0.5428,"expected_return_1d":{"mean_pct":0.22,"skew":0.01,"std_pct":0.32},"expected_return_3d":{"mean_pct":0.65,"skew":0.02,"std_pct":0.56},"p_stop_hit_1d":0.0,"p_stop_hit_3d":0.0,"p_up":0.752,"price_bands_1d":{"25":83.55,"5":83.29,"50":83.73,"75":83.91,"95":84.17},"price_bands_3d":{"25":83.77,"5":83.33,"50":84.09,"75":84.41,"95":84.86},"price_usd":83.55,"stop_price":82.06,"volatility_annual":0.05}},"portfolio_var":{"patient":{"cvar_95_sek":-461.51,"cvar_95_usd":-50.33,"cvar_99_usd":-75.75,"drawdown_1pct_prob":0.039,"drawdown_5pct_prob":0.0,"n_positions":1,"total_exposure_sek":36266.27,"total_exposure_usd":3954.88,"var_95_sek":-335.07,"var_95_usd":-36.54,"var_99_sek":-533.73,"var_99_usd":-58.2}}}