{"monte_carlo":{"AMZN":{"atr_pct":0.69,"drift_annual":0.494,"expected_return_1d":{"mean_pct":0.2,"skew":0.01,"std_pct":0.32},"expected_return_3d":{"mean_pct":0.59,"skew":0.02,"std_pct":0.55},"p_stop_hit_1d":0.0,"p_stop_hit_3d":0.0,"p_up":0.733,"price_bands_1d":{"25":207.27,"5":206.63,"50":207.71,"75":208.14,"95":208.79},"price_bands_3d":{"25":207.77,"5":206.65,"50":208.52,"75":209.27,"95":210.41},"price_usd":207.3,"stop_price":204.44,"volatility_annual":0.05},"BTC-USD":{"atr_pct":0.13,"drift_annual":-0.6668,"expected_return_1d":{"mean_pct":-0.26,"skew":0.01,"std_pct":0.31},"expected_return_3d":{"mean_pct":-0.79,"skew":0.02,"std_pct":0.54},"p_stop_hit_1d":0.505,"p_stop_hit_3d":0.839,"p_up":0.2,"price_bands_1d":{"25":70389.73,"5":70174.3,"50":70537.94,"75":70686.45,"95":70903.46},"price_bands_3d":{"25":69909.81,"5":69539.63,"50":70164.95,"75":70421.03,"95":70795.9},"price_usd":70725.17,"stop_price":70541.28,"volatility_annual":0.05},"META":{"atr_pct":0.85,"drift_annual":0.6693,"expected_return_1d":{"mean_pct":0.27,"skew":0.01,"std_pct":0.32},"expected_return_3d":{"mean_pct":0.8,"skew":0.02,"std_pct":0.55},"p_stop_hit_1d":0.0,"p_stop_hit_3d":0.0,"p_up":0.8,"price_bands_1d":{"25":611.2,"5":609.35,"50":612.52,"75":613.85,"95":615.71},"price_bands_3d":{"25":613.48,"5":610.27,"50":615.78,"75":618.09,"95":621.34},"price_usd":610.9,"stop_price":600.51,"volatility_annual":0.05},"SOUN":{"atr_pct":0.36,"drift_annual":-0.4513,"expected_return_1d":{"mean_pct":-0.18,"skew":0.01,"std_pct":0.32},"expected_return_3d":{"mean_pct":-0.54,"skew":0.02,"std_pct":0.55},"p_stop_hit_1d":0.045,"p_stop_hit_3d":0.366,"p_up":0.284,"price_bands_1d":{"25":7.29,"5":7.27,"50":7.31,"75":7.32,"95":7.35},"price_bands_3d":{"25":7.25,"5":7.21,"50":7.28,"75":7.31,"95":7.35},"price_usd":7.32,"stop_price":7.27,"volatility_annual":0.05},"VRT":{"atr_pct":0.4,"drift_annual":0.5515,"expected_return_1d":{"mean_pct":0.22,"skew":0.01,"std_pct":0.31},"expected_return_3d":{"mean_pct":0.66,"skew":0.02,"std_pct":0.54},"p_stop_hit_1d":0.0,"p_stop_hit_3d":0.004,"p_up":0.756,"price_bands_1d":{"25":258.01,"5":257.25,"50":258.56,"75":259.12,"95":259.89},"price_bands_3d":{"25":258.73,"5":257.41,"50":259.7,"75":260.67,"95":262.0},"price_usd":258.0,"stop_price":255.94,"volatility_annual":0.05},"XAG-USD":{"atr_pct":0.04,"drift_annual":0.0013,"expected_return_1d":{"mean_pct":0.0,"skew":0.01,"std_pct":0.31},"expected_return_3d":{"mean_pct":0.0,"skew":0.02,"std_pct":0.55},"p_stop_hit_1d":0.4,"p_stop_hit_3d":0.443,"p_up":0.5,"price_bands_1d":{"25":80.44,"5":80.21,"50":80.62,"75":80.8,"95":81.03},"price_bands_3d":{"25":80.32,"5":79.91,"50":80.62,"75":80.92,"95":81.33},"price_usd":80.62,"stop_price":80.56,"volatility_annual":0.05}},"portfolio_var":{"patient":{"cvar_95_sek":-457.67,"cvar_95_usd":-48.84,"cvar_99_usd":-75.43,"drawdown_1pct_prob":0.029,"drawdown_5pct_prob":0.0,"n_positions":1,"total_exposure_sek":38717.85,"total_exposure_usd":4132.11,"var_95_sek":-322.56,"var_95_usd":-34.43,"var_99_sek":-534.84,"var_99_usd":-57.08}}}