{"monte_carlo":{"AMD":{"atr_pct":1.67,"drift_annual":0.9139,"expected_return_1d":{"mean_pct":0.36,"skew":0.01,"std_pct":0.45},"expected_return_3d":{"mean_pct":1.09,"skew":0.02,"std_pct":0.78},"p_stop_hit_1d":0.0,"p_stop_hit_3d":0.0,"p_up":0.791,"price_bands_1d":{"25":197.73,"5":196.86,"50":198.32,"75":198.9,"95":199.79},"price_bands_3d":{"25":198.74,"5":197.22,"50":199.76,"75":200.78,"95":202.33},"price_usd":197.6,"stop_price":191.0,"volatility_annual":0.071},"AVGO":{"atr_pct":0.34,"drift_annual":0.54,"expected_return_1d":{"mean_pct":0.21,"skew":0.01,"std_pct":0.31},"expected_return_3d":{"mean_pct":0.64,"skew":0.02,"std_pct":0.54},"p_stop_hit_1d":0.002,"p_stop_hit_3d":0.007,"p_up":0.751,"price_bands_1d":{"25":335.51,"5":334.48,"50":336.22,"75":336.93,"95":337.96},"price_bands_3d":{"25":336.43,"5":334.65,"50":337.66,"75":338.89,"95":340.7},"price_usd":335.5,"stop_price":333.22,"volatility_annual":0.05},"BTC-USD":{"atr_pct":0.26,"drift_annual":-0.5032,"expected_return_1d":{"mean_pct":-0.2,"skew":0.01,"std_pct":0.32},"expected_return_3d":{"mean_pct":-0.6,"skew":0.02,"std_pct":0.55},"p_stop_hit_1d":0.157,"p_stop_hit_3d":0.557,"p_up":0.263,"price_bands_1d":{"25":70004.09,"5":69792.4,"50":70155.45,"75":70307.14,"95":70520.39},"price_bands_3d":{"25":69614.21,"5":69249.99,"50":69875.12,"75":70137.0,"95":70505.89},"price_usd":70296.04,"stop_price":69930.5,"volatility_annual":0.05},"GOOGL":{"atr_pct":1.05,"drift_annual":0.4163,"expected_return_1d":{"mean_pct":0.17,"skew":0.01,"std_pct":0.32},"expected_return_3d":{"mean_pct":0.5,"skew":0.02,"std_pct":0.55},"p_stop_hit_1d":0.0,"p_stop_hit_3d":0.0,"p_up":0.7,"price_bands_1d":{"25":304.14,"5":303.2,"50":304.79,"75":305.44,"95":306.4},"price_bands_3d":{"25":304.67,"5":303.03,"50":305.8,"75":306.93,"95":308.59},"price_usd":304.29,"stop_price":297.9,"volatility_annual":0.05},"META":{"atr_pct":3.37,"drift_annual":1.3456,"expected_return_1d":{"mean_pct":0.54,"skew":0.03,"std_pct":0.9},"expected_return_3d":{"mean_pct":1.61,"skew":0.04,"std_pct":1.57},"p_stop_hit_1d":0.0,"p_stop_hit_3d":0.0,"p_up":0.722,"price_bands_1d":{"25":638.76,"5":633.41,"50":642.72,"75":646.7,"95":652.16},"price_bands_3d":{"25":642.65,"5":633.37,"50":649.56,"75":656.55,"95":666.18},"price_usd":639.32,"stop_price":596.23,"volatility_annual":0.143},"XAG-USD":{"atr_pct":0.38,"drift_annual":0.6693,"expected_return_1d":{"mean_pct":0.27,"skew":0.01,"std_pct":0.32},"expected_return_3d":{"mean_pct":0.8,"skew":0.02,"std_pct":0.55},"p_stop_hit_1d":0.001,"p_stop_hit_3d":0.003,"p_up":0.8,"price_bands_1d":{"25":83.68,"5":83.44,"50":83.86,"75":84.04,"95":84.29},"price_bands_3d":{"25":83.99,"5":83.57,"50":84.31,"75":84.63,"95":85.05},"price_usd":83.64,"stop_price":83.0,"volatility_annual":0.05}},"portfolio_var":{"patient":{"cvar_95_sek":-284.91,"cvar_95_usd":-30.7,"cvar_99_usd":-56.17,"drawdown_1pct_prob":0.009,"drawdown_5pct_prob":0.0,"n_positions":1,"total_exposure_sek":36586.72,"total_exposure_usd":3942.53,"var_95_sek":-156.71,"var_95_usd":-16.89,"var_99_sek":-358.13,"var_99_usd":-38.59}}}