{"monte_carlo":{"AAPL":{"atr_pct":0.34,"drift_annual":0.4834,"expected_return_1d":{"mean_pct":0.19,"skew":0.01,"std_pct":0.32},"expected_return_3d":{"mean_pct":0.58,"skew":0.02,"std_pct":0.55},"p_stop_hit_1d":0.003,"p_stop_hit_3d":0.012,"p_up":0.728,"price_bands_1d":{"25":252.51,"5":251.72,"50":253.04,"75":253.57,"95":254.36},"price_bands_3d":{"25":253.09,"5":251.73,"50":254.01,"75":254.93,"95":256.31},"price_usd":252.555,"stop_price":250.84,"volatility_annual":0.05},"AMD":{"atr_pct":0.55,"drift_annual":0.3989,"expected_return_1d":{"mean_pct":0.16,"skew":0.01,"std_pct":0.31},"expected_return_3d":{"mean_pct":0.48,"skew":0.02,"std_pct":0.54},"p_stop_hit_1d":0.0,"p_stop_hit_3d":0.002,"p_up":0.692,"price_bands_1d":{"25":193.76,"5":193.17,"50":194.17,"75":194.57,"95":195.17},"price_bands_3d":{"25":194.07,"5":193.04,"50":194.78,"75":195.49,"95":196.53},"price_usd":193.86,"stop_price":191.73,"volatility_annual":0.05},"AMZN":{"atr_pct":0.42,"drift_annual":0.6497,"expected_return_1d":{"mean_pct":0.26,"skew":0.01,"std_pct":0.32},"expected_return_3d":{"mean_pct":0.78,"skew":0.02,"std_pct":0.55},"p_stop_hit_1d":0.0,"p_stop_hit_3d":0.002,"p_up":0.793,"price_bands_1d":{"25":207.8,"5":207.17,"50":208.25,"75":208.7,"95":209.33},"price_bands_3d":{"25":208.54,"5":207.45,"50":209.32,"75":210.1,"95":211.21},"price_usd":207.71,"stop_price":205.97,"volatility_annual":0.05},"AVGO":{"atr_pct":0.77,"drift_annual":0.4469,"expected_return_1d":{"mean_pct":0.18,"skew":0.01,"std_pct":0.32},"expected_return_3d":{"mean_pct":0.53,"skew":0.02,"std_pct":0.55},"p_stop_hit_1d":0.0,"p_stop_hit_3d":0.0,"p_up":0.713,"price_bands_1d":{"25":323.55,"5":322.54,"50":324.24,"75":324.93,"95":325.95},"price_bands_3d":{"25":324.19,"5":322.45,"50":325.39,"75":326.59,"95":328.36},"price_usd":323.67,"stop_price":318.69,"volatility_annual":0.05},"BTC-USD":{"atr_pct":0.64,"drift_annual":0.5427,"expected_return_1d":{"mean_pct":0.22,"skew":0.01,"std_pct":0.31},"expected_return_3d":{"mean_pct":0.65,"skew":0.02,"std_pct":0.54},"p_stop_hit_1d":0.0,"p_stop_hit_3d":0.0,"p_up":0.752,"price_bands_1d":{"25":71462.48,"5":71252.78,"50":71617.02,"75":71771.91,"95":71983.13},"price_bands_3d":{"25":71656.84,"5":71293.04,"50":71925.47,"75":72195.1,"95":72563.51},"price_usd":71463.3,"stop_price":70548.57,"volatility_annual":0.05},"ETH-USD":{"atr_pct":0.87,"drift_annual":0.547,"expected_return_1d":{"mean_pct":0.22,"skew":0.01,"std_pct":0.32},"expected_return_3d":{"mean_pct":0.65,"skew":0.02,"std_pct":0.55},"p_stop_hit_1d":0.0,"p_stop_hit_3d":0.0,"p_up":0.754,"price_bands_1d":{"25":2117.43,"5":2111.26,"50":2122.04,"75":2126.66,"95":2132.87},"price_bands_3d":{"25":2123.25,"5":2112.54,"50":2131.25,"75":2139.29,"95":2150.13},"price_usd":2117.45,"stop_price":2080.61,"volatility_annual":0.05},"META":{"atr_pct":0.44,"drift_annual":0.6693,"expected_return_1d":{"mean_pct":0.27,"skew":0.01,"std_pct":0.32},"expected_return_3d":{"mean_pct":0.8,"skew":0.02,"std_pct":0.55},"p_stop_hit_1d":0.0,"p_stop_hit_3d":0.002,"p_up":0.8,"price_bands_1d":{"25":618.38,"5":616.48,"50":619.71,"75":621.04,"95":622.96},"price_bands_3d":{"25":620.7,"5":617.38,"50":623.0,"75":625.32,"95":628.68},"price_usd":618.07,"stop_price":612.63,"volatility_annual":0.05},"NVDA":{"atr_pct":0.48,"drift_annual":-0.3162,"expected_return_1d":{"mean_pct":-0.13,"skew":0.01,"std_pct":0.32},"expected_return_3d":{"mean_pct":-0.38,"skew":0.02,"std_pct":0.55},"p_stop_hit_1d":0.004,"p_stop_hit_3d":0.145,"p_up":0.345,"price_bands_1d":{"25":180.56,"5":180.0,"50":180.95,"75":181.35,"95":181.91},"price_bands_3d":{"25":179.82,"5":178.86,"50":180.5,"75":181.18,"95":182.15},"price_usd":181.18,"stop_price":179.44,"volatility_annual":0.05},"PLTR":{"atr_pct":0.76,"drift_annual":0.4914,"expected_return_1d":{"mean_pct":0.2,"skew":0.01,"std_pct":0.31},"expected_return_3d":{"mean_pct":0.59,"skew":0.02,"std_pct":0.54},"p_stop_hit_1d":0.0,"p_stop_hit_3d":0.0,"p_up":0.732,"price_bands_1d":{"25":150.35,"5":149.89,"50":150.67,"75":150.99,"95":151.45},"price_bands_3d":{"25":150.69,"5":149.91,"50":151.25,"75":151.82,"95":152.61},"price_usd":150.375,"stop_price":148.09,"volatility_annual":0.05},"SMCI":{"atr_pct":0.84,"drift_annual":0.4919,"expected_return_1d":{"mean_pct":0.2,"skew":0.01,"std_pct":0.31},"expected_return_3d":{"mean_pct":0.59,"skew":0.02,"std_pct":0.54},"p_stop_hit_1d":0.0,"p_stop_hit_3d":0.0,"p_up":0.732,"price_bands_1d":{"25":30.3,"5":30.21,"50":30.36,"75":30.43,"95":30.52},"price_bands_3d":{"25":30.37,"5":30.21,"50":30.48,"75":30.59,"95":30.75},"price_usd":30.305,"stop_price":29.8,"volatility_annual":0.05},"SOUN":{"atr_pct":1.03,"drift_annual":0.4632,"expected_return_1d":{"mean_pct":0.18,"skew":0.01,"std_pct":0.31},"expected_return_3d":{"mean_pct":0.55,"skew":0.02,"std_pct":0.55},"p_stop_hit_1d":0.0,"p_stop_hit_3d":0.0,"p_up":0.72,"price_bands_1d":{"25":7.3,"5":7.28,"50":7.31,"75":7.33,"95":7.35},"price_bands_3d":{"25":7.31,"5":7.27,"50":7.34,"75":7.37,"95":7.41},"price_usd":7.3,"stop_price":7.15,"volatility_annual":0.05},"VRT":{"atr_pct":0.96,"drift_annual":0.6528,"expected_return_1d":{"mean_pct":0.26,"skew":0.01,"std_pct":0.32},"expected_return_3d":{"mean_pct":0.78,"skew":0.02,"std_pct":0.55},"p_stop_hit_1d":0.0,"p_stop_hit_3d":0.0,"p_up":0.794,"price_bands_1d":{"25":259.7,"5":258.9,"50":260.24,"75":260.79,"95":261.6},"price_bands_3d":{"25":260.65,"5":259.25,"50":261.59,"75":262.54,"95":263.95},"price_usd":259.57,"stop_price":254.59,"volatility_annual":0.05},"XAG-USD":{"atr_pct":0.92,"drift_annual":0.4458,"expected_return_1d":{"mean_pct":0.18,"skew":0.01,"std_pct":0.32},"expected_return_3d":{"mean_pct":0.53,"skew":0.02,"std_pct":0.55},"p_stop_hit_1d":0.0,"p_stop_hit_3d":0.0,"p_up":0.712,"price_bands_1d":{"25":80.09,"5":79.85,"50":80.26,"75":80.43,"95":80.68},"price_bands_3d":{"25":80.25,"5":79.83,"50":80.55,"75":80.84,"95":81.27},"price_usd":80.12,"stop_price":78.65,"volatility_annual":0.05},"XAU-USD":{"atr_pct":0.35,"drift_annual":0.4376,"expected_return_1d":{"mean_pct":0.17,"skew":0.01,"std_pct":0.32},"expected_return_3d":{"mean_pct":0.52,"skew":0.02,"std_pct":0.56},"p_stop_hit_1d":0.003,"p_stop_hit_3d":0.012,"p_up":0.709,"price_bands_1d":{"25":5037.01,"5":5020.84,"50":5047.79,"75":5058.61,"95":5074.89},"price_bands_3d":{"25":5046.57,"5":5018.55,"50":5065.31,"75":5084.11,"95":5112.5},"price_usd":5039.06,"stop_price":5003.79,"volatility_annual":0.05}},"portfolio_var":{"patient":{"cvar_95_sek":-494.69,"cvar_95_usd":-52.8,"cvar_99_usd":-79.17,"drawdown_1pct_prob":0.041,"drawdown_5pct_prob":0.0,"n_positions":1,"total_exposure_sek":38449.27,"total_exposure_usd":4103.44,"var_95_sek":-360.67,"var_95_usd":-38.49,"var_99_sek":-571.25,"var_99_usd":-60.97}}}